setup.py
yueyegame/__init__.py
yueyegame/game.py
yueyegame.egg-info/PKG-INFO
yueyegame.egg-info/SOURCES.txt
yueyegame.egg-info/dependency_links.txt
yueyegame.egg-info/top_level.txt